ogb/__init__.py
ogb/version.py
ogb/graphproppred/__init__.py
ogb/graphproppred/dataset.py
ogb/graphproppred/dataset_dgl.py
ogb/graphproppred/dataset_pyg.py
ogb/graphproppred/evaluate.py
ogb/graphproppred/make_master_file.py
ogb/graphproppred/master.csv
ogb/graphproppred/mol_encoder.py
ogb/io/__init__.py
ogb/io/read_graph_dgl.py
ogb/io/read_graph_pyg.py
ogb/io/read_graph_raw.py
ogb/io/save_dataset.py
ogb/linkproppred/__init__.py
ogb/linkproppred/dataset.py
ogb/linkproppred/dataset_dgl.py
ogb/linkproppred/dataset_pyg.py
ogb/linkproppred/evaluate.py
ogb/linkproppred/make_master_file.py
ogb/linkproppred/master.csv
ogb/lsc/__init__.py
ogb/lsc/mag240m.py
ogb/lsc/pcqm4m.py
ogb/lsc/pcqm4m_dgl.py
ogb/lsc/pcqm4m_pyg.py
ogb/lsc/pcqm4mv2.py
ogb/lsc/pcqm4mv2_dgl.py
ogb/lsc/pcqm4mv2_pyg.py
ogb/lsc/utils.py
ogb/lsc/wikikg90m.py
ogb/lsc/wikikg90mv2.py
ogb/nodeproppred/__init__.py
ogb/nodeproppred/dataset.py
ogb/nodeproppred/dataset_dgl.py
ogb/nodeproppred/dataset_pyg.py
ogb/nodeproppred/evaluate.py
ogb/nodeproppred/make_master_file.py
ogb/nodeproppred/master.csv
ogb/utils/__init__.py
ogb/utils/features.py
ogb/utils/mol.py
ogb/utils/torch_util.py
ogb/utils/url.py
ogb-1.3.6.dist-info/LICENSE
ogb-1.3.6.dist-info/METADATA
ogb-1.3.6.dist-info/WHEEL
ogb-1.3.6.dist-info/top_level.txt
ogb-1.3.6.dist-info/RECORD
