Metadata-Version: 2.1
Name: ogb
Version: 1.3.6
Summary: Open Graph Benchmark
Home-page: https://github.com/snap-stanford/ogb
Author: OGB Team
Author-email: ogb@cs.stanford.edu
License: MIT
Keywords: pytorch,graph machine learning,graph representation learning,graph neural networks
Platform: UNKNOWN
Classifier: Topic :: Scientific/Engineering :: Artificial Intelligence
Classifier: Intended Audience :: Science/Research
Classifier: Programming Language :: Python :: 3.6
Classifier: Programming Language :: Python :: 3.7
Classifier: License :: OSI Approved :: MIT License
